src/tcare-sbv/__init__.py
src/tcare-sbv/sb_validator.py
v/bin/rst2html.py
v/bin/rst2html4.py
v/bin/rst2html5.py
v/bin/rst2latex.py
v/bin/rst2man.py
v/bin/rst2odt.py
v/bin/rst2odt_prepstyles.py
v/bin/rst2pseudoxml.py
v/bin/rst2s5.py
v/bin/rst2xetex.py
v/bin/rst2xml.py
v/bin/rstpep2html.py
tcare_sbv-0.0.2.dist-info/METADATA
tcare_sbv-0.0.2.dist-info/WHEEL
tcare_sbv-0.0.2.dist-info/licenses/LICENSE.txt
tcare_sbv-0.0.2.dist-info/RECORD
