Metadata-Version: 2.1
Name: tcare-sbv
Version: 0.0.2
Summary: Validate that servicebus messages are in the correct format
Project-URL: Homepage, https://github.com/TCARE1/tcare-sbv-package
Project-URL: Bug Tracker, https://github.com/TCARE1/tcare-sbv-package/issues
Author-email: TCARE <elijah.kennedy@tcare.ai>
License-File: LICENSE.txt
Classifier: License :: OSI Approved :: MIT License
Classifier: Operating System :: OS Independent
Classifier: Programming Language :: Python :: 3
Requires-Python: >=3.7
